text_profiler/__init__.py
text_profiler/profiler.py
text_profiler-0.1.1.dist-info/METADATA
text_profiler-0.1.1.dist-info/WHEEL
text_profiler-0.1.1.dist-info/top_level.txt
text_profiler-0.1.1.dist-info/RECORD
