Metadata-Version: 2.4
Name: text-profiler
Version: 0.1.1
Summary: A simple library for quick text statistics and profiling.
Home-page: https://github.com/yourusername/text_profiler
Author: Khadija Bhanpurawala
Author-email: khadijabhanpurawala52@gmail.com
Classifier: Programming Language :: Python :: 3
Classifier: License :: OSI Approved :: MIT License
Classifier: Operating System :: OS Independent
Classifier: Topic :: Text Processing :: Linguistic
Requires-Python: >=3.6
Dynamic: author
Dynamic: author-email
Dynamic: classifier
Dynamic: description
Dynamic: description-content-type
Dynamic: home-page
Dynamic: requires-python
Dynamic: summary
